CONTRIBUTORS
LICENSE
MANIFEST.in
README.rst
setup.py
brake/__init__.py
brake/decorators.py
brake/models.py
brake/utils.py
brake/backends/__init__.py
brake/backends/cachebe.py
brake/backends/dummybe.py
brake/tests/__init__.py
brake/tests/custom_backend.py
brake/tests/tests.py
django_brake.egg-info/PKG-INFO
django_brake.egg-info/SOURCES.txt
django_brake.egg-info/dependency_links.txt
django_brake.egg-info/requires.txt
django_brake.egg-info/top_level.txt